AUTHORS.rst
LICENSE
MANIFEST.in
README.md
setup.cfg
setup.py
pyyelp/__init__.py
pyyelp/exceptions.py
pyyelp/pyyelp.py
pyyelp.egg-info/PKG-INFO
pyyelp.egg-info/SOURCES.txt
pyyelp.egg-info/dependency_links.txt
pyyelp.egg-info/requires.txt
pyyelp.egg-info/top_level.txt
requirements/base.txt