Metadata-Version: 1.1
Name: pyyelp
Version: 0.1
Summary: Python wrapper for the Yelp v2 api
Home-page: https://github.com/motte/python-yelp
Author: Michael Otte
Author-email: michaelotte2013@gmail.com
License: ISC
Download-URL: https://github.com/motte/python-yelp/tarball/0.1
Keywords: yelp,wrapper,api
Platform: UNKNOWN
Classifier: Programming Language :: Python
Classifier: Programming Language :: Python :: 2.6
Classifier: Programming Language :: Python :: 2.7
Classifier: License :: OSI Approved :: ISC License (ISCL)
Classifier: Operating System :: OS Independent
Classifier: Development Status :: 2 - Pre-Alpha
Classifier: Intended Audience :: Developers
